my_fake_useragent/__init__.py
my_fake_useragent/const.py
my_fake_useragent/crawler.py
my_fake_useragent/filter.py
my_fake_useragent/parsed_data.py
my_fake_useragent/utils.py
my_fake_useragent-0.2.1.dist-info/LICENSE
my_fake_useragent-0.2.1.dist-info/METADATA
my_fake_useragent-0.2.1.dist-info/WHEEL
my_fake_useragent-0.2.1.dist-info/top_level.txt
my_fake_useragent-0.2.1.dist-info/RECORD
