Metadata-Version: 2.1
Name: my-fake-useragent
Version: 0.2.1
Summary: create a fake useragent
Home-page: https://github.com/a358003542/my-fake-useragent
Author: wanze
Author-email: a358003542@gmail.com
Maintainer: wanze
Maintainer-email: a358003542@gmail.com
License: MIT
Keywords: useragent,python
Classifier: Development Status :: 4 - Beta
Classifier: Operating System :: Microsoft :: Windows
Classifier: Operating System :: POSIX :: Linux
Classifier: License :: OSI Approved :: MIT License
Classifier: Programming Language :: Python :: 3
License-File: LICENSE
